{
  "manifest": [
    {
      "key": "assets/items/item_quest_gp5.bundle",
      "dependencyKeys": []
    },
    {
      "key": "assets/clothing/hands/hands_boss_killa.bundle",
      "dependencyKeys": []
    },
    {
      "key": "assets/clothing/tops/top_boss_tagilla.bundle",
      "dependencyKeys": []
    },
    {
      "key": "assets/clothing/bottoms/pants_boss_tagilla.bundle",
      "dependencyKeys": []
    },
    {
      "key": "assets/clothing/hands/hands_boss_takilla.bundle",
      "dependencyKeys": []
    }

  ]
}